{
  "rabbit_version": "3.13",
  "parameters": [
    {
      "value": {
        "x-delayed-type": "direct"
      },
      "vhost": "/",
      "component": "exchange",
      "name": "delayed-message"
    }
  ],
  "policies": [],
  "queues": [
    {"name": "quartz", "vhost": "/", "durable": true, "auto_delete": false, "arguments": {}}
  ],
  "exchanges": [
    {"name": "delayed-message", "vhost": "/", "type": "x-delayed-message", "durable": true, "auto_delete": false, "internal": false, "arguments": {"x-delayed-type": "direct"}}
  ],
  "bindings": []
}
